MANIFEST.in
README.txt
setup.py
docs/HISTORY.txt
docs/INSTALL.txt
docs/LICENSE.GPL
docs/LICENSE.txt
z3c/__init__.py
z3c.requestlet.egg-info/PKG-INFO
z3c.requestlet.egg-info/SOURCES.txt
z3c.requestlet.egg-info/dependency_links.txt
z3c.requestlet.egg-info/entry_points.txt
z3c.requestlet.egg-info/namespace_packages.txt
z3c.requestlet.egg-info/not-zip-safe
z3c.requestlet.egg-info/paster_plugins.txt
z3c.requestlet.egg-info/requires.txt
z3c.requestlet.egg-info/top_level.txt
z3c/requestlet/__init__.py
z3c/requestlet/configure.zcml
z3c/requestlet/interfaces.py
z3c/requestlet/rlog.py
z3c/requestlet/tests.py
z3c/requestlet/browser/__init__.py
z3c/requestlet/browser/configure.zcml
z3c/requestlet/browser/rlog.pt
z3c/requestlet/browser/rlog.py
z3c/requestlet/browser/data/flotter.js
z3c/requestlet/browser/data/generate_graph.py
z3c/requestlet/browser/data/jquery.js
z3c/requestlet/browser/data/layout.css
z3c/requestlet/browser/data/requestlet.txt
z3c/requestlet/browser/data/flot/excanvas.js
z3c/requestlet/browser/data/flot/excanvas.pack.js
z3c/requestlet/browser/data/flot/jquery.flot.js
z3c/requestlet/profiles/default/browserlayer.xml
z3c/requestlet/profiles/default/metadata.xml