Metadata-Version: 1.0
Name: z3c.requestlet
Version: 0.9
Summary: UNKNOWN
Home-page: http://d9t.de/os
Author: Daniel Kraft, Stefan Eletzhofer
Author-email: dk@d9t.de, info@inquant.de
License: GPL
Platform: UNKNOWN
Classifier: Framework :: Plone
Classifier: Programming Language :: Python
Classifier: Topic :: Software Development :: Libraries :: Python Modules
